libname/__init__.py
libname/ratzetpasswordgenerator03.py
ratzetpasswordgenerator03-0.0.1.dist-info/METADATA
ratzetpasswordgenerator03-0.0.1.dist-info/WHEEL
ratzetpasswordgenerator03-0.0.1.dist-info/top_level.txt
ratzetpasswordgenerator03-0.0.1.dist-info/RECORD
